Workbook

Sheet Flip Tracker
A1: VINTAGE SCOUT — Flip Tracker
A2: Track every acquisition, sale, and profit. All yellow cells are formulas — just fill in the blue input columns.
A4: # | B4: Date Acquired | C4: Source | D4: Brand / Designer | E4: Item Description | F4: Category | G4: Buy Price | H4: Repair Cost | I4: Total Cost | J4: Date Listed | K4: Date Sold | L4: Sale Platform | M4: Sale Price | N4: Platform Fee % | O4: Platform Fee $ | P4: Net Revenue | Q4: Profit $ | R4: Margin % | S4: ROI % | T4: Days to Sell | U4: Status
A5: 1 | B5: 46091 | C5: Swoopa Alert | D5: Broyhill | E5: Brasilia credenza walnut 6-drawer | F5: MCM Furniture | G5: 45 | H5: 20 | I5: =IF(G5="","",G5+IF(H5="",0,H5)) -> 65 | J5: 46093 | K5: 46096 | L5: FB Marketplace | M5: 425 | N5: 0 | O5: =IF(OR(M5="",N5=""),"",M5*N5) -> 0 | P5: =IF(M5="","",M5-IF(O5="",0,O5)) -> 425 | Q5: =IF(OR(P5="",I5=""),"",P5-I5) -> 360 | R5: =IF(OR(Q5="",M5="",M5=0),"",Q5/M5) -> 0.84705882 | S5: =IF(OR(Q5="",I5="",I5=0),"",Q5/I5) -> 5.5384615 | T5: =IF(OR(K5="",J5=""),"",K5-J5) -> 3 | U5: Sold
A6: 2 | B6: 46093 | C6: Free/Curb | D6: Unknown (Danish) | E6: Teak dining table, leaf, solid wood | F6: Danish Modern | G6: 0 | H6: 35 | I6: =IF(G6="","",G6+IF(H6="",0,H6)) -> 35 | J6: 46095 | K6: 46101 | L6: Craigslist | M6: 280 | N6: 0 | O6: =IF(OR(M6="",N6=""),"",M6*N6) -> 0 | P6: =IF(M6="","",M6-IF(O6="",0,O6)) -> 280 | Q6: =IF(OR(P6="",I6=""),"",P6-I6) -> 245 | R6: =IF(OR(Q6="",M6="",M6=0),"",Q6/M6) -> 0.875 | S6: =IF(OR(Q6="",I6="",I6=0),"",Q6/I6) -> 7 | T6: =IF(OR(K6="",J6=""),"",K6-J6) -> 6 | U6: Sold
A7: 3 | B7: 46096 | C7: Craigslist | D7: Vintage Levi's | E7: 501 Big E selvedge denim, 32x34 | F7: Vintage Denim | G7: 12 | H7: 0 | I7: =IF(G7="","",G7+IF(H7="",0,H7)) -> 12 | J7: 46097 | K7: 46099 | L7: eBay | M7: 165 | N7: 0.13 | O7: =IF(OR(M7="",N7=""),"",M7*N7) -> 21.45 | P7: =IF(M7="","",M7-IF(O7="",0,O7)) -> 143.55 | Q7: =IF(OR(P7="",I7=""),"",P7-I7) -> 131.55 | R7: =IF(OR(Q7="",M7="",M7=0),"",Q7/M7) -> 0.79727273 | S7: =IF(OR(Q7="",I7="",I7=0),"",Q7/I7) -> 10.9625 | T7: =IF(OR(K7="",J7=""),"",K7-J7) -> 2 | U7: Sold
A8: 4 | I8: =IF(G8="","",G8+IF(H8="",0,H8)) | O8: =IF(OR(M8="",N8=""),"",M8*N8) | P8: =IF(M8="","",M8-IF(O8="",0,O8)) | Q8: =IF(OR(P8="",I8=""),"",P8-I8) | R8: =IF(OR(Q8="",M8="",M8=0),"",Q8/M8) | S8: =IF(OR(Q8="",I8="",I8=0),"",Q8/I8) | T8: =IF(OR(K8="",J8=""),"",K8-J8)
A9: 5 | I9: =IF(G9="","",G9+IF(H9="",0,H9)) | O9: =IF(OR(M9="",N9=""),"",M9*N9) | P9: =IF(M9="","",M9-IF(O9="",0,O9)) | Q9: =IF(OR(P9="",I9=""),"",P9-I9) | R9: =IF(OR(Q9="",M9="",M9=0),"",Q9/M9) | S9: =IF(OR(Q9="",I9="",I9=0),"",Q9/I9) | T9: =IF(OR(K9="",J9=""),"",K9-J9)
A10: 6 | I10: =IF(G10="","",G10+IF(H10="",0,H10)) | O10: =IF(OR(M10="",N10=""),"",M10*N10) | P10: =IF(M10="","",M10-IF(O10="",0,O10)) | Q10: =IF(OR(P10="",I10=""),"",P10-I10) | R10: =IF(OR(Q10="",M10="",M10=0),"",Q10/M10) | S10: =IF(OR(Q10="",I10="",I10=0),"",Q10/I10) | T10: =IF(OR(K10="",J10=""),"",K10-J10)
A11: 7 | I11: =IF(G11="","",G11+IF(H11="",0,H11)) | O11: =IF(OR(M11="",N11=""),"",M11*N11) | P11: =IF(M11="","",M11-IF(O11="",0,O11)) | Q11: =IF(OR(P11="",I11=""),"",P11-I11) | R11: =IF(OR(Q11="",M11="",M11=0),"",Q11/M11) | S11: =IF(OR(Q11="",I11="",I11=0),"",Q11/I11) | T11: =IF(OR(K11="",J11=""),"",K11-J11)
A12: 8 | I12: =IF(G12="","",G12+IF(H12="",0,H12)) | O12: =IF(OR(M12="",N12=""),"",M12*N12) | P12: =IF(M12="","",M12-IF(O12="",0,O12)) | Q12: =IF(OR(P12="",I12=""),"",P12-I12) | R12: =IF(OR(Q12="",M12="",M12=0),"",Q12/M12) | S12: =IF(OR(Q12="",I12="",I12=0),"",Q12/I12) | T12: =IF(OR(K12="",J12=""),"",K12-J12)
A13: 9 | I13: =IF(G13="","",G13+IF(H13="",0,H13)) | O13: =IF(OR(M13="",N13=""),"",M13*N13) | P13: =IF(M13="","",M13-IF(O13="",0,O13)) | Q13: =IF(OR(P13="",I13=""),"",P13-I13) | R13: =IF(OR(Q13="",M13="",M13=0),"",Q13/M13) | S13: =IF(OR(Q13="",I13="",I13=0),"",Q13/I13) | T13: =IF(OR(K13="",J13=""),"",K13-J13)
A14: 10 | I14: =IF(G14="","",G14+IF(H14="",0,H14)) | O14: =IF(OR(M14="",N14=""),"",M14*N14) | P14: =IF(M14="","",M14-IF(O14="",0,O14)) | Q14: =IF(OR(P14="",I14=""),"",P14-I14) | R14: =IF(OR(Q14="",M14="",M14=0),"",Q14/M14) | S14: =IF(OR(Q14="",I14="",I14=0),"",Q14/I14) | T14: =IF(OR(K14="",J14=""),"",K14-J14)
A15: 11 | I15: =IF(G15="","",G15+IF(H15="",0,H15)) | O15: =IF(OR(M15="",N15=""),"",M15*N15) | P15: =IF(M15="","",M15-IF(O15="",0,O15)) | Q15: =IF(OR(P15="",I15=""),"",P15-I15) | R15: =IF(OR(Q15="",M15="",M15=0),"",Q15/M15) | S15: =IF(OR(Q15="",I15="",I15=0),"",Q15/I15) | T15: =IF(OR(K15="",J15=""),"",K15-J15)
A16: 12 | I16: =IF(G16="","",G16+IF(H16="",0,H16)) | O16: =IF(OR(M16="",N16=""),"",M16*N16) | P16: =IF(M16="","",M16-IF(O16="",0,O16)) | Q16: =IF(OR(P16="",I16=""),"",P16-I16) | R16: =IF(OR(Q16="",M16="",M16=0),"",Q16/M16) | S16: =IF(OR(Q16="",I16="",I16=0),"",Q16/I16) | T16: =IF(OR(K16="",J16=""),"",K16-J16)
A17: 13 | I17: =IF(G17="","",G17+IF(H17="",0,H17)) | O17: =IF(OR(M17="",N17=""),"",M17*N17) | P17: =IF(M17="","",M17-IF(O17="",0,O17)) | Q17: =IF(OR(P17="",I17=""),"",P17-I17) | R17: =IF(OR(Q17="",M17="",M17=0),"",Q17/M17) | S17: =IF(OR(Q17="",I17="",I17=0),"",Q17/I17) | T17: =IF(OR(K17="",J17=""),"",K17-J17)
A18: 14 | I18: =IF(G18="","",G18+IF(H18="",0,H18)) | O18: =IF(OR(M18="",N18=""),"",M18*N18) | P18: =IF(M18="","",M18-IF(O18="",0,O18)) | Q18: =IF(OR(P18="",I18=""),"",P18-I18) | R18: =IF(OR(Q18="",M18="",M18=0),"",Q18/M18) | S18: =IF(OR(Q18="",I18="",I18=0),"",Q18/I18) | T18: =IF(OR(K18="",J18=""),"",K18-J18)
A19: 15 | I19: =IF(G19="","",G19+IF(H19="",0,H19)) | O19: =IF(OR(M19="",N19=""),"",M19*N19) | P19: =IF(M19="","",M19-IF(O19="",0,O19)) | Q19: =IF(OR(P19="",I19=""),"",P19-I19) | R19: =IF(OR(Q19="",M19="",M19=0),"",Q19/M19) | S19: =IF(OR(Q19="",I19="",I19=0),"",Q19/I19) | T19: =IF(OR(K19="",J19=""),"",K19-J19)
... A54: 50 | I54: =IF(G54="","",G54+IF(H54="",0,H54)) | O54: =IF(OR(M54="",N54=""),"",M54*N54) | P54: =IF(M54="","",M54-IF(O54="",0,O54)) | Q54: =IF(OR(P54="",I54=""),"",P54-I54) | R54: =IF(OR(Q54="",M54="",M54=0),"",Q54/M54) | S54: =IF(OR(Q54="",I54="",I54=0),"",Q54/I54) | T54: =IF(OR(K54="",J54=""),"",K54-J54)

Sheet Dashboard
A1: DASHBOARD — Performance Summary
A3: Total Flips | D3: Items Sold | G3: Total Revenue | J3: Total Cost | M3: Total Profit
A4: =COUNTA('Flip Tracker'!U5:U54)-COUNTBLANK('Flip Tracker'!U5:U54) -> -44 | D4: =COUNTIF('Flip Tracker'!U5:U54,"Sold") -> 3 | G4: =SUMPRODUCT((('Flip Tracker'!U5:U54)="Sold")*1*('Flip Tracker'!M5:M54)) -> 870 | J4: =SUMPRODUCT((('Flip Tracker'!U5:U54)="Sold")*1*('Flip Tracker'!G5:G54)) -> 57 | M4: =SUMPRODUCT((('Flip Tracker'!U5:U54)="Sold")*1*('Flip Tracker'!M5:M54))-SUMPRODUCT((('Flip Tracker'!U5:U54)="Sold")*1*('Flip Tracker'!G5:G54)) -> 813
A6: Avg Profit/Flip | D6: Avg Margin | G6: Avg ROI | J6: Avg Days to Sell | M6: In Inventory
A7: =IF(COUNTIF('Flip Tracker'!U5:U54,"Sold")=0,"",(SUMPRODUCT((('Flip Tracker'!U5:U54)="Sold")*1*('Flip Tracker'!M5:M54))-SUMPRODUCT((('Flip Tracker'!U5:U54)="Sold")*1*('Flip Tracker'!G5:G54)))/COUNTIF('Flip Tracker'!U5:U54,"Sold")) -> 271 | D7: =IF(COUNTIF('Flip Tracker'!U5:U54,"Sold")=0,"",1-SUMPRODUCT((('Flip Tracker'!U5:U54)="Sold")*1*('Flip Tracker'!G5:G54))/SUMPRODUCT((('Flip Tracker'!U5:U54)="Sold")*1*('Flip Tracker'!M5:M54))) -> 0.93448276 | G7: =IF(COUNTIF('Flip Tracker'!U5:U54,"Sold")=0,"",(SUMPRODUCT((('Flip Tracker'!U5:U54)="Sold")*1*('Flip Tracker'!M5:M54))/SUMPRODUCT((('Flip Tracker'!U5:U54)="Sold")*1*('Flip Tracker'!G5:G54)))-1) -> 14.263158 | J7: =IF(COUNTIF('Flip Tracker'!U5:U54,"Sold")=0,"",SUMPRODUCT((('Flip Tracker'!U5:U54)="Sold")*('Flip Tracker'!K5:K54-'Flip Tracker'!J5:J54))/COUNTIF('Flip Tracker'!U5:U54,"Sold")) -> 3.6666667 | M7: =COUNTIF('Flip Tracker'!U5:U54,"Acquired")+COUNTIF('Flip Tracker'!U5:U54,"Repairing")+COUNTIF('Flip Tracker'!U5:U54,"Listed") -> 0
A9: Platform Fee Reference | E9: Monthly Targets
A10: Platform | B10: Typical Fee % | E10: Month | F10: Flips | G10: Revenue | H10: Profit | I10: Target Profit | J10: Hit?
A11: FB Marketplace | B11: 0% (local) | E11: Jan | J11: =IF(OR(H11="",I11=""),"",IF(H11>=I11,"✓","✕"))
A12: Craigslist | B12: 0% | E12: Feb | J12: =IF(OR(H12="",I12=""),"",IF(H12>=I12,"✓","✕"))
A13: eBay | B13: 13% | E13: Mar | J13: =IF(OR(H13="",I13=""),"",IF(H13>=I13,"✓","✕"))
A14: 1stDibs | B14: 15-25% | E14: Apr | J14: =IF(OR(H14="",I14=""),"",IF(H14>=I14,"✓","✕"))
A15: Chairish | B15: 30% | E15: May | J15: =IF(OR(H15="",I15=""),"",IF(H15>=I15,"✓","✕"))
A16: Poshmark | B16: 20% | E16: Jun | J16: =IF(OR(H16="",I16=""),"",IF(H16>=I16,"✓","✕"))
A17: Depop | B17: 10% | E17: Jul | J17: =IF(OR(H17="",I17=""),"",IF(H17>=I17,"✓","✕"))
A18: Instagram/Direct | B18: 0% | E18: Aug | J18: =IF(OR(H18="",I18=""),"",IF(H18>=I18,"✓","✕"))
E19: Sep | J19: =IF(OR(H19="",I19=""),"",IF(H19>=I19,"✓","✕"))
E20: Oct | J20: =IF(OR(H20="",I20=""),"",IF(H20>=I20,"✓","✕"))
E21: Nov | J21: =IF(OR(H21="",I21=""),"",IF(H21>=I21,"✓","✕"))
E22: Dec | J22: =IF(OR(H22="",I22=""),"",IF(H22>=I22,"✓","✕"))

Sheet Active Inventory
A1: ACTIVE INVENTORY — Items Not Yet Sold
A2: These rows auto-populate from Flip Tracker where Status ≠ Sold. Fill in estimated resale to track potential pipeline value.
A4: Brand / Designer | B4: Item Description | C4: Category | D4: Date Acquired | E4: Total Cost | F4: Status | G4: Est. Resale Low | H4: Est. Resale High | I4: Est. Profit (mid) | J4: Days Held | K4: Notes
I5: =IF(OR(G5="",H5="",E5=""),"",(G5+H5)/2-E5) | J5: =IF(D5="","",TODAY()-D5)
I6: =IF(OR(G6="",H6="",E6=""),"",(G6+H6)/2-E6) | J6: =IF(D6="","",TODAY()-D6)
I7: =IF(OR(G7="",H7="",E7=""),"",(G7+H7)/2-E7) | J7: =IF(D7="","",TODAY()-D7)
I8: =IF(OR(G8="",H8="",E8=""),"",(G8+H8)/2-E8) | J8: =IF(D8="","",TODAY()-D8)
I9: =IF(OR(G9="",H9="",E9=""),"",(G9+H9)/2-E9) | J9: =IF(D9="","",TODAY()-D9)
I10: =IF(OR(G10="",H10="",E10=""),"",(G10+H10)/2-E10) | J10: =IF(D10="","",TODAY()-D10)
I11: =IF(OR(G11="",H11="",E11=""),"",(G11+H11)/2-E11) | J11: =IF(D11="","",TODAY()-D11)
I12: =IF(OR(G12="",H12="",E12=""),"",(G12+H12)/2-E12) | J12: =IF(D12="","",TODAY()-D12)
I13: =IF(OR(G13="",H13="",E13=""),"",(G13+H13)/2-E13) | J13: =IF(D13="","",TODAY()-D13)
I14: =IF(OR(G14="",H14="",E14=""),"",(G14+H14)/2-E14) | J14: =IF(D14="","",TODAY()-D14)
I15: =IF(OR(G15="",H15="",E15=""),"",(G15+H15)/2-E15) | J15: =IF(D15="","",TODAY()-D15)
I16: =IF(OR(G16="",H16="",E16=""),"",(G16+H16)/2-E16) | J16: =IF(D16="","",TODAY()-D16)
... I24: =IF(OR(G24="",H24="",E24=""),"",(G24+H24)/2-E24) | J24: =IF(D24="","",TODAY()-D24)
A26: Pipeline Value: | C26: =SUM(I5:I24) -> 0
A27: Total Invested: | C27: =SUM(E5:E24) -> 0
